.class public entradaJasmin
.super java/lang/Object

.method public <init>()V
   aload_0

   invokenonvirtual java/lang/Object/<init>()V
   return
.end method

.method public static main([Ljava/lang/String;)V
   .limit stack 2
   .limit locals 7
   bipush 10
   istore 1
   bipush 100
   istore 2
   iload 2
   iload 1
   idiv
   istore 3
   getstatic java/lang/System/out Ljava/io/PrintStream;
   iload 3
   invokevirtual java/io/PrintStream/println(I)V
   iload 3
   iconst_1
   iadd
   istore 3
   getstatic java/lang/System/out Ljava/io/PrintStream;
   iload 3
   invokevirtual java/io/PrintStream/println(I)V
   ldc "Amanda"
   astore 4
   ldc " Rodrigues\n"
   astore 6
   ldc "Leonardo"
   astore 5
   getstatic java/lang/System/out Ljava/io/PrintStream;
   aload 4
   invokevirtual java/io/PrintStream/print(Ljava/lang/String;)V
   getstatic java/lang/System/out Ljava/io/PrintStream;
   aload 6
   invokevirtual java/io/PrintStream/print(Ljava/lang/String;)V
   getstatic java/lang/System/out Ljava/io/PrintStream;
   aload 5
   invokevirtual java/io/PrintStream/print(Ljava/lang/String;)V
   getstatic java/lang/System/out Ljava/io/PrintStream;
   aload 6
   invokevirtual java/io/PrintStream/print(Ljava/lang/String;)V
   return
.end method
